AkvoDjangoFormGateway/__init__.py
AkvoDjangoFormGateway/admin.py
AkvoDjangoFormGateway/apps.py
AkvoDjangoFormGateway/constants.py
AkvoDjangoFormGateway/feed.py
AkvoDjangoFormGateway/models.py
AkvoDjangoFormGateway/serializers.py
AkvoDjangoFormGateway/urls.py
AkvoDjangoFormGateway/views.py
AkvoDjangoFormGateway/management/__init__.py
AkvoDjangoFormGateway/management/commands/__init__.py
AkvoDjangoFormGateway/management/commands/fake_gateway_data_seeder.py
AkvoDjangoFormGateway/management/commands/gateway_form_seeder.py
AkvoDjangoFormGateway/management/commands/gateway_geo_converter.py
AkvoDjangoFormGateway/migrations/0001_initial.py
AkvoDjangoFormGateway/migrations/0002_alter_akvogatewaydata_options.py
AkvoDjangoFormGateway/migrations/__init__.py
AkvoDjangoFormGateway/tests/__init__.py
AkvoDjangoFormGateway/tests/tests_data_endpoint.py
AkvoDjangoFormGateway/tests/tests_data_serializers.py
AkvoDjangoFormGateway/tests/tests_env.py
AkvoDjangoFormGateway/tests/tests_form_serializer.py
AkvoDjangoFormGateway/tests/tests_geo_converter.py
AkvoDjangoFormGateway/tests/tests_geo_question.py
AkvoDjangoFormGateway/tests/tests_init.py
AkvoDjangoFormGateway/tests/tests_question_serializer.py
AkvoDjangoFormGateway/tests/tests_seeder_command.py
AkvoDjangoFormGateway/tests/tests_twilio_endpoint.py
AkvoDjangoFormGateway/tests/tests_twilio_instance_endpoint.py
AkvoDjangoFormGateway/tests/tests_validation.py
AkvoDjangoFormGateway/utils/__init__.py
AkvoDjangoFormGateway/utils/functions.py
AkvoDjangoFormGateway/utils/services.py
AkvoDjangoFormGateway/utils/validation.py
AkvoDjangoFormGateway-0.0.9.dist-info/LICENSE
AkvoDjangoFormGateway-0.0.9.dist-info/METADATA
AkvoDjangoFormGateway-0.0.9.dist-info/WHEEL
AkvoDjangoFormGateway-0.0.9.dist-info/top_level.txt
AkvoDjangoFormGateway-0.0.9.dist-info/RECORD
