Metadata-Version: 2.1
Name: AkvoDjangoFormGateway
Version: 0.0.9
Summary: A Django library that enables seamless integration of messenger services
Home-page: https://github.com/akvo/Akvo-DjangoFormGateway
Author: Akvo
Author-email: tech.consultancy@akvo.org
Maintainer: Deden Bangkit
Maintainer-email: deden@akvo.org
Project-URL: Documentation, https://github.com/akvo/Akvo-DjangoFormGateway
Project-URL: Bug Reports, https://github.com/akvo/Akvo-DjangoFormGateway/issues
Project-URL: Source Code, https://github.com/akvo/Akvo-DjangoFormGateway
Keywords: akvo,twilio,whatsapp,ssid,sms,django
Classifier: Development Status :: 4 - Beta
Classifier: Intended Audience :: Developers
Classifier: License :: Public Domain
Classifier: Operating System :: OS Independent
Classifier: Programming Language :: Python
Classifier: Programming Language :: Python :: 3
Classifier: Programming Language :: Python :: 3.8
Classifier: Programming Language :: Python :: 3.9
Classifier: Programming Language :: Python :: 3.10
Classifier: Programming Language :: Python :: 3.11
Classifier: Programming Language :: Python :: 3 :: Only
Classifier: Programming Language :: Python :: Implementation :: CPython
Classifier: Programming Language :: Python :: Implementation :: PyPy
Classifier: Framework :: Django
Classifier: Framework :: Django :: 4.0
Classifier: Framework :: Django :: 4.1
Classifier: Operating System :: OS Independent
Classifier: Topic :: Internet :: WWW/HTTP
Requires-Python: >=3.8.5
License-File: LICENSE
Requires-Dist: setuptools (>=36.2)
Requires-Dist: twilio (>=8.2.0)
Requires-Dist: djangorestframework (>=3.12.4)
Requires-Dist: requests (==2.26.0)
Requires-Dist: Django (>=4.0.4)
Provides-Extra: dev
Requires-Dist: check-manifest ; extra == 'dev'
